<stg><name>lab_1</name>


<trans_list>
</trans_list>



<state_list>

<state id="1" st_id="1">

<operation id="2" st_id="1" stage="1" lat="1">
<core>NULL</core>
<MemPortIdVec></MemPortIdVec>
<condition id="-1">
<or_exp><and_exp></and_exp></or_exp>
</condition>

<Node id="5" bw="0" op_0_bw="0" op_1_bw="32">
<![CDATA[
:0  call void (...)* @_ssdm_op_SpecBitsMap(i32 %A_V), !map !46

]]></Node>
<StgValue><ssdm name="specbitsmap_ln0"/></StgValue>
</operation>

<operation id="3" st_id="1" stage="1" lat="1">
<core>NULL</core>
<MemPortIdVec></MemPortIdVec>
<condition id="-1">
<or_exp><and_exp></and_exp></or_exp>
</condition>

<Node id="6" bw="0" op_0_bw="0" op_1_bw="32">
<![CDATA[
:1  call void (...)* @_ssdm_op_SpecBitsMap(i32 %B_V), !map !52

]]></Node>
<StgValue><ssdm name="specbitsmap_ln0"/></StgValue>
</operation>

<operation id="4" st_id="1" stage="1" lat="1">
<core>NULL</core>
<MemPortIdVec></MemPortIdVec>
<condition id="-1">
<or_exp><and_exp></and_exp></or_exp>
</condition>

<Node id="7" bw="0" op_0_bw="0" op_1_bw="32">
<![CDATA[
:2  call void (...)* @_ssdm_op_SpecBitsMap(i32 %C_V), !map !56

]]></Node>
<StgValue><ssdm name="specbitsmap_ln0"/></StgValue>
</operation>

<operation id="5" st_id="1" stage="1" lat="1">
<core>NULL</core>
<MemPortIdVec></MemPortIdVec>
<condition id="-1">
<or_exp><and_exp></and_exp></or_exp>
</condition>

<Node id="8" bw="0" op_0_bw="0" op_1_bw="32">
<![CDATA[
:3  call void (...)* @_ssdm_op_SpecBitsMap(i32* %Y_V), !map !60

]]></Node>
<StgValue><ssdm name="specbitsmap_ln0"/></StgValue>
</operation>

<operation id="6" st_id="1" stage="1" lat="1">
<core>NULL</core>
<MemPortIdVec></MemPortIdVec>
<condition id="-1">
<or_exp><and_exp></and_exp></or_exp>
</condition>

<Node id="9" bw="0" op_0_bw="0" op_1_bw="0">
<![CDATA[
:4  call void (...)* @_ssdm_op_SpecTopModule([6 x i8]* @lab_1_str) nounwind

]]></Node>
<StgValue><ssdm name="spectopmodule_ln0"/></StgValue>
</operation>

<operation id="7" st_id="1" stage="1" lat="1">
<core>s_axilite</core>
<MemPortIdVec></MemPortIdVec>
<condition id="-1">
<or_exp><and_exp></and_exp></or_exp>
</condition>

<Node id="10" bw="32" op_0_bw="32" op_1_bw="32">
<![CDATA[
:5  %C_V_read = call i32 @_ssdm_op_Read.s_axilite.i32(i32 %C_V)

]]></Node>
<StgValue><ssdm name="C_V_read"/></StgValue>
</operation>

<operation id="8" st_id="1" stage="1" lat="1">
<core>s_axilite</core>
<MemPortIdVec></MemPortIdVec>
<condition id="-1">
<or_exp><and_exp></and_exp></or_exp>
</condition>

<Node id="11" bw="32" op_0_bw="32" op_1_bw="32">
<![CDATA[
:6  %B_V_read = call i32 @_ssdm_op_Read.s_axilite.i32(i32 %B_V)

]]></Node>
<StgValue><ssdm name="B_V_read"/></StgValue>
</operation>

<operation id="9" st_id="1" stage="1" lat="1">
<core>s_axilite</core>
<MemPortIdVec></MemPortIdVec>
<condition id="-1">
<or_exp><and_exp></and_exp></or_exp>
</condition>

<Node id="12" bw="32" op_0_bw="32" op_1_bw="32">
<![CDATA[
:7  %A_V_read = call i32 @_ssdm_op_Read.s_axilite.i32(i32 %A_V)

]]></Node>
<StgValue><ssdm name="A_V_read"/></StgValue>
</operation>

<operation id="10" st_id="1" stage="1" lat="1">
<core>NULL</core>
<MemPortIdVec></MemPortIdVec>
<condition id="-1">
<or_exp><and_exp></and_exp></or_exp>
</condition>

<Node id="13" bw="0" op_0_bw="0" op_1_bw="32" op_2_bw="0" op_3_bw="32" op_4_bw="32" op_5_bw="0" op_6_bw="32" op_7_bw="32" op_8_bw="0" op_9_bw="0" op_10_bw="0" op_11_bw="32" op_12_bw="32" op_13_bw="32" op_14_bw="32" op_15_bw="0" op_16_bw="0">
<![CDATA[
:8  call void (...)* @_ssdm_op_SpecInterface(i32 0, [13 x i8]* @p_str, i32 0, i32 0, [1 x i8]* @p_str1, i32 0, i32 0, [1 x i8]* @p_str1, [1 x i8]* @p_str1, [1 x i8]* @p_str1, i32 0, i32 0, i32 0, i32 0, [1 x i8]* @p_str1, [1 x i8]* @p_str1) nounwind

]]></Node>
<StgValue><ssdm name="specinterface_ln4"/></StgValue>
</operation>

<operation id="11" st_id="1" stage="1" lat="1">
<core>NULL</core>
<MemPortIdVec></MemPortIdVec>
<condition id="-1">
<or_exp><and_exp></and_exp></or_exp>
</condition>

<Node id="14" bw="0" op_0_bw="0" op_1_bw="32" op_2_bw="0" op_3_bw="32" op_4_bw="32" op_5_bw="0" op_6_bw="32" op_7_bw="32" op_8_bw="0" op_9_bw="0" op_10_bw="0" op_11_bw="32" op_12_bw="32" op_13_bw="32" op_14_bw="32" op_15_bw="0" op_16_bw="0">
<![CDATA[
:9  call void (...)* @_ssdm_op_SpecInterface(i32 %A_V, [10 x i8]* @p_str2, i32 0, i32 0, [1 x i8]* @p_str1, i32 0, i32 0, [1 x i8]* @p_str1, [1 x i8]* @p_str1, [1 x i8]* @p_str1, i32 0, i32 0, i32 0, i32 0, [1 x i8]* @p_str1, [1 x i8]* @p_str1) nounwind

]]></Node>
<StgValue><ssdm name="specinterface_ln4"/></StgValue>
</operation>

<operation id="12" st_id="1" stage="1" lat="1">
<core>NULL</core>
<MemPortIdVec></MemPortIdVec>
<condition id="-1">
<or_exp><and_exp></and_exp></or_exp>
</condition>

<Node id="15" bw="0" op_0_bw="0" op_1_bw="32" op_2_bw="0" op_3_bw="32" op_4_bw="32" op_5_bw="0" op_6_bw="32" op_7_bw="32" op_8_bw="0" op_9_bw="0" op_10_bw="0" op_11_bw="32" op_12_bw="32" op_13_bw="32" op_14_bw="32" op_15_bw="0" op_16_bw="0">
<![CDATA[
:10  call void (...)* @_ssdm_op_SpecInterface(i32 %B_V, [10 x i8]* @p_str2, i32 0, i32 0, [1 x i8]* @p_str1, i32 0, i32 0, [1 x i8]* @p_str1, [1 x i8]* @p_str1, [1 x i8]* @p_str1, i32 0, i32 0, i32 0, i32 0, [1 x i8]* @p_str1, [1 x i8]* @p_str1) nounwind

]]></Node>
<StgValue><ssdm name="specinterface_ln4"/></StgValue>
</operation>

<operation id="13" st_id="1" stage="1" lat="1">
<core>NULL</core>
<MemPortIdVec></MemPortIdVec>
<condition id="-1">
<or_exp><and_exp></and_exp></or_exp>
</condition>

<Node id="16" bw="0" op_0_bw="0" op_1_bw="32" op_2_bw="0" op_3_bw="32" op_4_bw="32" op_5_bw="0" op_6_bw="32" op_7_bw="32" op_8_bw="0" op_9_bw="0" op_10_bw="0" op_11_bw="32" op_12_bw="32" op_13_bw="32" op_14_bw="32" op_15_bw="0" op_16_bw="0">
<![CDATA[
:11  call void (...)* @_ssdm_op_SpecInterface(i32 %C_V, [10 x i8]* @p_str2, i32 0, i32 0, [1 x i8]* @p_str1, i32 0, i32 0, [1 x i8]* @p_str1, [1 x i8]* @p_str1, [1 x i8]* @p_str1, i32 0, i32 0, i32 0, i32 0, [1 x i8]* @p_str1, [1 x i8]* @p_str1) nounwind

]]></Node>
<StgValue><ssdm name="specinterface_ln4"/></StgValue>
</operation>

<operation id="14" st_id="1" stage="1" lat="1">
<core>NULL</core>
<MemPortIdVec></MemPortIdVec>
<condition id="-1">
<or_exp><and_exp></and_exp></or_exp>
</condition>

<Node id="17" bw="0" op_0_bw="0" op_1_bw="32" op_2_bw="0" op_3_bw="32" op_4_bw="32" op_5_bw="0" op_6_bw="32" op_7_bw="32" op_8_bw="0" op_9_bw="0" op_10_bw="0" op_11_bw="32" op_12_bw="32" op_13_bw="32" op_14_bw="32" op_15_bw="0" op_16_bw="0">
<![CDATA[
:12  call void (...)* @_ssdm_op_SpecInterface(i32* %Y_V, [10 x i8]* @p_str2, i32 0, i32 0, [1 x i8]* @p_str1, i32 0, i32 0, [1 x i8]* @p_str1, [1 x i8]* @p_str1, [1 x i8]* @p_str1, i32 0, i32 0, i32 0, i32 0, [1 x i8]* @p_str1, [1 x i8]* @p_str1) nounwind

]]></Node>
<StgValue><ssdm name="specinterface_ln4"/></StgValue>
</operation>

<operation id="15" st_id="1" stage="1" lat="1">
<core>NULL</core>
<MemPortIdVec></MemPortIdVec>
<condition id="-1">
<or_exp><and_exp></and_exp></or_exp>
</condition>

<Node id="18" bw="32" op_0_bw="32" op_1_bw="32">
<![CDATA[
:13  %shl_ln68 = shl i32 %B_V_read, 1

]]></Node>
<StgValue><ssdm name="shl_ln68"/></StgValue>
</operation>

<operation id="16" st_id="1" stage="1" lat="1">
<core>TAddSub</core>
<MemPortIdVec></MemPortIdVec>
<condition id="-1">
<or_exp><and_exp></and_exp></or_exp>
</condition>

<Node id="19" bw="32" op_0_bw="32" op_1_bw="32">
<![CDATA[
:14  %add_ln68 = add i32 %A_V_read, %shl_ln68

]]></Node>
<StgValue><ssdm name="add_ln68"/></StgValue>
</operation>

<operation id="17" st_id="1" stage="1" lat="1">
<core>TAddSub</core>
<MemPortIdVec></MemPortIdVec>
<condition id="-1">
<or_exp><and_exp></and_exp></or_exp>
</condition>

<Node id="20" bw="32" op_0_bw="32" op_1_bw="32">
<![CDATA[
:15  %sub_ln68 = sub i32 %add_ln68, %C_V_read

]]></Node>
<StgValue><ssdm name="sub_ln68"/></StgValue>
</operation>

<operation id="18" st_id="1" stage="1" lat="1">
<core>s_axilite</core>
<MemPortIdVec></MemPortIdVec>
<condition id="-1">
<or_exp><and_exp></and_exp></or_exp>
</condition>

<Node id="21" bw="0" op_0_bw="0" op_1_bw="32" op_2_bw="32">
<![CDATA[
:16  call void @_ssdm_op_Write.s_axilite.i32P(i32* %Y_V, i32 %sub_ln68)

]]></Node>
<StgValue><ssdm name="write_ln4"/></StgValue>
</operation>

<operation id="19" st_id="1" stage="1" lat="1">
<core>NULL</core>
<MemPortIdVec></MemPortIdVec>
<condition id="-1">
<or_exp><and_exp></and_exp></or_exp>
</condition>

<Node id="22" bw="0">
<![CDATA[
:17  ret void

]]></Node>
<StgValue><ssdm name="ret_ln5"/></StgValue>
</operation>
</state>
</state_list>


<ports>
</ports>


<dataflows>
</dataflows>


</stg>
